py_cherty/__init__.py
py_cherty/git_utils.py
py_cherty/py_cherty.py
py_cherty-1.2.1.dist-info/LICENSE
py_cherty-1.2.1.dist-info/METADATA
py_cherty-1.2.1.dist-info/WHEEL
py_cherty-1.2.1.dist-info/top_level.txt
py_cherty-1.2.1.dist-info/RECORD
