Metadata-Version: 2.1
Name: py_cherty
Version: 1.2.1
Summary: A package to send messages to an Electron app
Home-page: https://github.com/devonian-ai/py_cherty
Author: Alan Ransil
Author-email: alan@devonian.ai
Classifier: Programming Language :: Python :: 3
Classifier: License :: OSI Approved :: MIT License
Classifier: Operating System :: OS Independent
Requires-Python: >=3.6
License-File: LICENSE
